{
    "context": "server",
    "identifier": "com.pa.dreadnought.dreadnought_balance_mod",
    "display_name": "Dreadnought Balance Mod",
    "description": "Makes various balance changes to units for testing and theory crafting, specific details on forums or in notepad info",
    "author": "Dreadnought",
    "version": "1.42",
    "date": "2022-2-24",
    "build": "115853",
    "signature": " meh ",
    "priority": 95,
    "enabled": true,
    "icon": "https://i.imgur.com/tUPAmBC.png",
    "forum": "https://forums.planetaryannihilation.com/threads/wip-server-dreadnought-balance-mod.73524/ ",
    "fileSystem": false,
    "searchable": [
        "adjustments",
        "units",
        "change",
        "stats",
        "balance",
        "dreadnought"
    ],
    "sort": "Dreadnought Balance Mod",
    "authors": [
		"Dreadnought"
    ],
    "dependencies": [],
    "companions": [],
    "scenes": {},
    "framework": false,
    "available": true,
    "titansOnly": true,
    "classicOnly": false,
    "classic": false,
    "titans": true,
    "conflicts": {}
}